switch_hacker/__init__.py
switch_hacker/auto_play.py
switch_hacker/base.py
switch_hacker/experiment.py
switch_hacker/game.py
switch_hacker/hacker.py
switch_hacker/strategy.py
switch_hacker-0.0.1.dist-info/METADATA
switch_hacker-0.0.1.dist-info/WHEEL
switch_hacker-0.0.1.dist-info/licenses/LICENSE
switch_hacker-0.0.1.dist-info/RECORD
