Metadata-Version: 2.1
Name: switch_hacker
Version: 0.0.1
Summary: A hack way to play switch game
Project-URL: Homepage, https://github.com/luochang212/hit-and-blow
Project-URL: Bug Tracker, https://github.com/luochang212/hit-and-blow/issues
Author-email: luochang212 <luochang212@gmail.com>
License-File: LICENSE
Classifier: License :: OSI Approved :: MIT License
Classifier: Operating System :: OS Independent
Classifier: Programming Language :: Python :: 3
Requires-Python: >=3.7
